firestore_pydantic_odm/__init__.py
firestore_pydantic_odm/enums.py
firestore_pydantic_odm/firestore_client.py
firestore_pydantic_odm/firestore_fields.py
firestore_pydantic_odm/firestore_model.py
firestore_pydantic_odm/pydantic_compat.py
firestore_pydantic_odm-0.2.6.dist-info/LICENSE
firestore_pydantic_odm-0.2.6.dist-info/METADATA
firestore_pydantic_odm-0.2.6.dist-info/WHEEL
firestore_pydantic_odm-0.2.6.dist-info/top_level.txt
firestore_pydantic_odm-0.2.6.dist-info/RECORD
