Metadata-Version: 2.1
Name: firestore-pydantic-odm
Version: 0.2.6
Summary: Asynchronous Pydantic ODM for Google Cloud Firestore
Home-page: https://github.com/santosdevco/firestore-pydantic-odm
Author: Santos Dev Co
Author-email: projects@santosdevco.com
License: MIT
Project-URL: Documentation, https://github.com/santosdevco/firestore-pydantic-odm#readme
Project-URL: Changelog, https://github.com/santosdevco/firestore-pydantic-odm/releases
Project-URL: Issue Tracker, https://github.com/santosdevco/firestore-pydantic-odm/issues
Project-URL: Source Code, https://github.com/santosdevco/firestore-pydantic-odm
Keywords: firestore,pydantic,odm,asyncio,google cloud
Classifier: Development Status :: 4 - Beta
Classifier: Intended Audience :: Developers
Classifier: License :: OSI Approved :: MIT License
Classifier: Operating System :: OS Independent
Classifier: Programming Language :: Python :: 3
Classifier: Programming Language :: Python :: 3 :: Only
Classifier: Programming Language :: Python :: 3.8
Classifier: Programming Language :: Python :: 3.9
Classifier: Programming Language :: Python :: 3.10
Classifier: Programming Language :: Python :: 3.11
Classifier: Framework :: AsyncIO
Classifier: Topic :: Database :: Front-Ends
Classifier: Typing :: Typed
Requires-Python: >=3.8
License-File: LICENSE
Requires-Dist: pydantic<3.0.0,>=1.5
Requires-Dist: google-cloud-firestore>=2.0.0
Provides-Extra: dev
Requires-Dist: black; extra == "dev"
Requires-Dist: ruff; extra == "dev"
Requires-Dist: pytest; extra == "dev"
Requires-Dist: pytest-asyncio; extra == "dev"
Provides-Extra: emulator
Requires-Dist: google-cloud-firestore-emulator; extra == "emulator"
